{
	"info": {
		"_postman_id": "38760255-3569-4996-8ffa-dda87e32b1ff",
		"name": "Teste Intuitive Care - Pedro",
		"schema": "https://schema.getpostman.com/json/collection/v2.1.0/collection.json",
		"_exporter_id": "44666294"
	},
	"item": [
		{
			"name": "Buscar Operadoras (Unimed)",
			"protocolProfileBehavior": {
				"disableBodyPruning": true
			},
			"request": {
				"method": "GET",
				"header": [],
				"body": {
					"mode": "graphql",
					"graphql": {
						"query": "",
						"variables": ""
					}
				},
				"url": {
					"raw": "http://localhost:5000/operadoras?q=unimed",
					"protocol": "http",
					"host": [
						"localhost"
					],
					"port": "5000",
					"path": [
						"operadoras"
					],
					"query": [
						{
							"key": "q",
							"value": "unimed"
						}
					]
				}
			},
			"response": []
		}
	]
}